[
  {
    "firstname" : "Default Admin",
    "lastname" : "Admin",
    "user":
    {
      "username": "Admin",
      "password": "admin123"
    }
  },
  {
    "firstname" : "Papenzi",
    "middlename" : "Ben",
    "lastname" : "sarr",
    "user": {
      "username": "Pazi12356",
      "password": "pap1234567"
    }
  },
  {
    "firstname" : "Mathieu",
    "middlename" : "Ben",
    "lastname" : "Batthieu",
    "gender": "M",
    "birthdate" : "2000-12-01",
    "user": {
      "username": "ben1325",
      "password": "Moma123456"
    }
  }
]
